file_counter_server/__init__.py
file_counter_server/mcp.py
file_counter_server-0.1.0.dist-info/METADATA
file_counter_server-0.1.0.dist-info/WHEEL
file_counter_server-0.1.0.dist-info/entry_points.txt
file_counter_server-0.1.0.dist-info/RECORD
