Metadata-Version: 2.4
Name: file-counter-server
Version: 0.1.0
Summary: Add your description here
Author-email: 郭国勇 <guoyong.ggy@autonavi.com>
Requires-Python: >=3.10
Requires-Dist: mcp[cli]>=1.8.1
